drops/__init__.py
drops/core.py
drops/drops_old.py
drops/futures.py
drops/conf/__init__.py
drops/conf/project_template/__init__.py
drops/conf/project_template/settings.py
drops/conf/project_template/sim.py
drops/conf/project_template/domain/__init__.py
drops_py-0.0.1.dist-info/METADATA
drops_py-0.0.1.dist-info/WHEEL
drops_py-0.0.1.dist-info/top_level.txt
drops_py-0.0.1.dist-info/RECORD
